jsonsniffer/__init__.py
jsonsniffer/base.py
jsonsniffer/decorators.py
jsonsniffer/exceptions.py
jsonsniffer/fields.py
jsonsniffer/schema.py
jsonsniffer-0.0.1a0.dist-info/DESCRIPTION.rst
jsonsniffer-0.0.1a0.dist-info/METADATA
jsonsniffer-0.0.1a0.dist-info/RECORD
jsonsniffer-0.0.1a0.dist-info/WHEEL
jsonsniffer-0.0.1a0.dist-info/metadata.json
jsonsniffer-0.0.1a0.dist-info/top_level.txt
