Metadata-Version: 2.0
Name: jsonsniffer
Version: 0.0.1a0
Summary: A simple library for parsing complex json data to and from Python datatypes
Home-page: https://github.com/ArtemAngelchev/JsonSniffer.git
Author: Angelchev Artem
Author-email: artangelchev@gmail.com
License: MIT
Keywords: serialization,deserialization,json,schema,validation
Platform: UNKNOWN
Classifier: Intended Audience :: Developers
Classifier: Programming Language :: Python :: 3.6
Classifier: Programming Language :: Python :: 3 :: Only
Requires-Dist: jmespath
